odoo/addons/base_tier_validation/README.rst
odoo/addons/base_tier_validation/__init__.py
odoo/addons/base_tier_validation/__manifest__.py
odoo/addons/base_tier_validation/i18n/base_tier_validation.pot
odoo/addons/base_tier_validation/i18n/es.po
odoo/addons/base_tier_validation/migrations/11.0.1.2.0/post-migrate.py
odoo/addons/base_tier_validation/models/__init__.py
odoo/addons/base_tier_validation/models/res_users.py
odoo/addons/base_tier_validation/models/tier_definition.py
odoo/addons/base_tier_validation/models/tier_review.py
odoo/addons/base_tier_validation/models/tier_validation.py
odoo/addons/base_tier_validation/readme/CONFIGURE.rst
odoo/addons/base_tier_validation/readme/CONTRIBUTORS.rst
odoo/addons/base_tier_validation/readme/DESCRIPTION.rst
odoo/addons/base_tier_validation/readme/ROADMAP.rst
odoo/addons/base_tier_validation/security/ir.model.access.csv
odoo/addons/base_tier_validation/static/description/icon.png
odoo/addons/base_tier_validation/static/description/index.html
odoo/addons/base_tier_validation/static/src/js/systray.js
odoo/addons/base_tier_validation/static/src/js/tier_review_widget.js
odoo/addons/base_tier_validation/static/src/less/review.less
odoo/addons/base_tier_validation/static/src/less/systray.less
odoo/addons/base_tier_validation/static/src/xml/systray.xml
odoo/addons/base_tier_validation/static/src/xml/tier_review_template.xml
odoo/addons/base_tier_validation/tests/__init__.py
odoo/addons/base_tier_validation/tests/common.py
odoo/addons/base_tier_validation/tests/test_tier_validation.py
odoo/addons/base_tier_validation/tests/tier_validation_tester.py
odoo/addons/base_tier_validation/views/assets_backend.xml
odoo/addons/base_tier_validation/views/tier_definition_view.xml
odoo/addons/base_tier_validation/views/tier_review_view.xml
odoo11_addon_base_tier_validation-11.0.3.1.1.dist-info/METADATA
odoo11_addon_base_tier_validation-11.0.3.1.1.dist-info/WHEEL
odoo11_addon_base_tier_validation-11.0.3.1.1.dist-info/top_level.txt
odoo11_addon_base_tier_validation-11.0.3.1.1.dist-info/RECORD
